[
  {
    "item": "Item",
    "brand": "Test",
    "size": "",
    "color": "",
    "type": [],
    "style": [],
    "material": [],
    "count": 50,
    "quantity": 100,
    "notes": "",
    "bin": [
      14
    ]
  },
  {
    "item": "backpack",
    "brand": "",
    "size": "",
    "color": "",
    "type": [],
    "style": [],
    "material": [],
    "count": 1,
    "quantity": 10,
    "notes": "",
    "bin": [
      21,
      31
    ]
  },
  {
    "item": "binder",
    "brand": "",
    "size": "1 inch",
    "color": "",
    "type": [
      "3-ring"
    ],
    "style": [],
    "material": [],
    "count": 1,
    "quantity": 56,
    "notes": "",
    "bin": [
      15,
      23
    ]
  },
  {
    "item": "binder",
    "brand": "",
    "size": "0.5 inch",
    "color": "",
    "type": [
      "3-ring"
    ],
    "style": [],
    "material": [],
    "count": 1,
    "quantity": 1,
    "notes": "",
    "bin": [
      5,
      24,
      32
    ]
  },
  {
    "item": "blanket",
    "brand": "",
    "size": "small",
    "color": "",
    "type": [],
    "style": [],
    "material": [],
    "count": 1,
    "quantity": 23,
    "notes": "",
    "bin": [
      26
    ]
  },
  {
    "item": "book bag",
    "brand": "",
    "size": "",
    "color": "",
    "type": [],
    "style": [],
    "material": [],
    "count": 1,
    "quantity": 124,
    "notes": "no wheels",
    "bin": [
      9,
      30
    ]
  },
  {
    "item": "bowls",
    "brand": "",
    "size": "",
    "color": "",
    "type": [],
    "style": [],
    "material": [
      "non-coated paper"
    ],
    "count": 1,
    "quantity": 5,
    "notes": "",
    "bin": [
      22,
      24,
      28
    ]
  }
]
